isTrue/__init__.py
isTrue/isTrue.py
isTrue-0.0.20.dist-info/LICENSE.txt
isTrue-0.0.20.dist-info/METADATA
isTrue-0.0.20.dist-info/WHEEL
isTrue-0.0.20.dist-info/top_level.txt
isTrue-0.0.20.dist-info/RECORD
