Metadata-Version: 2.1
Name: isTrue
Version: 0.0.20
Summary: WHAAAAAAAAAAAAAAAT???
Keywords: IDWHAAAAAAAAAAAAAAATWHAAAAAAAAAAAAAAATK???
Classifier: Development Status :: 5 - Production/Stable
Classifier: Intended Audience :: Developers
Classifier: License :: Other/Proprietary License
Classifier: License :: Free To Use But Restricted
Classifier: Operating System :: OS Independent
Classifier: Programming Language :: Python :: 3
Requires-Python: >=3.4
License-File: LICENSE.txt
